{"nodes":[{"id":"2020165","x":-8479373.3,"y":17549694.1,"majorLevel":null,"majorInt":"N","eligible":true,"outsideGa":true},{"id":"2020182","x":-8465757.7,"y":17541309.3,"majorLevel":null,"majorInt":"N","eligible":true,"outsideGa":true},{"id":"2020195","x":-8446719.6,"y":17533753.2,"majorLevel":null,"majorInt":"N","eligible":true,"outsideGa":true},{"id":"2020199","x":-8444097.5,"y":17532936.9,"majorLevel":null,"majorInt":"N","eligible":true,"outsideGa":true},{"id":"2020205","x":-8439453.0,"y":17531633.7,"majorLevel":null,"majorInt":"N","eligible":true,"outsideGa":true},{"id":"2020213","x":-8428874.7,"y":17524043.0,"majorLevel":null,"majorInt":"N","eligible":true,"outsideGa":true},{"id":"2020215","x":-8427890.1,"y":17522350.9,"majorLevel":null,"majorInt":"N","eligible":true,"outsideGa":true},{"id":"2020217","x":-8427029.5,"y":17520735.7,"majorLevel":null,"majorInt":"N","eligible":true,"outsideGa":true}]}