{"nodes":[{"id":"2033229","x":-849214.4,"y":12956302.1,"majorLevel":null,"majorInt":"N","eligible":true,"outsideGa":true},{"id":"2033233","x":-847879.3,"y":12950559.5,"majorLevel":null,"majorInt":"N","eligible":true,"outsideGa":true},{"id":"2033243","x":-846464.1,"y":12952716.1,"majorLevel":null,"majorInt":"N","eligible":true,"outsideGa":true},{"id":"2033250","x":-845926.6,"y":12951694.1,"majorLevel":null,"majorInt":"N","eligible":true,"outsideGa":true},{"id":"2033255","x":-845414.9,"y":12950601.0,"majorLevel":null,"majorInt":"N","eligible":true,"outsideGa":true},{"id":"2033263","x":-844140.2,"y":12922205.3,"majorLevel":null,"majorInt":"N","eligible":true,"outsideGa":true},{"id":"2033265","x":-843958.1,"y":12952811.3,"majorLevel":null,"majorInt":"N","eligible":true,"outsideGa":true},{"id":"2033309","x":-836399.1,"y":12942240.2,"majorLevel":null,"majorInt":"N","eligible":true,"outsideGa":true}]}