{"nodes":[{"id":"2021200","x":-7112947.3,"y":13116780.7,"majorLevel":null,"majorInt":"N","eligible":true,"outsideGa":true},{"id":"2021221","x":-7099664.6,"y":13064719.1,"majorLevel":null,"majorInt":"N","eligible":true,"outsideGa":true},{"id":"2021222","x":-7099248.3,"y":13062164.0,"majorLevel":null,"majorInt":"N","eligible":true,"outsideGa":true},{"id":"2021224","x":-7098915.9,"y":13060178.7,"majorLevel":null,"majorInt":"N","eligible":true,"outsideGa":true},{"id":"2021225","x":-7098321.3,"y":13056004.2,"majorLevel":null,"majorInt":"N","eligible":true,"outsideGa":true},{"id":"2021227","x":-7097824.2,"y":13040700.5,"majorLevel":null,"majorInt":"N","eligible":true,"outsideGa":true},{"id":"2021228","x":-7097717.9,"y":13041929.5,"majorLevel":null,"majorInt":"N","eligible":true,"outsideGa":true}]}