{"nodes":[{"id":"2045916","x":1682837.8,"y":13751589.0,"majorLevel":null,"majorInt":"N","eligible":true,"outsideGa":true},{"id":"2045943","x":1691062.9,"y":13749657.7,"majorLevel":null,"majorInt":"N","eligible":true,"outsideGa":true},{"id":"2045944","x":1691547.6,"y":13749531.0,"majorLevel":null,"majorInt":"N","eligible":true,"outsideGa":true},{"id":"2045972","x":1700372.7,"y":13745209.1,"majorLevel":null,"majorInt":"N","eligible":true,"outsideGa":true},{"id":"2045977","x":1700994.4,"y":13744186.3,"majorLevel":null,"majorInt":"N","eligible":true,"outsideGa":true},{"id":"2046027","x":1725504.5,"y":13739995.3,"majorLevel":null,"majorInt":"N","eligible":true,"outsideGa":true}]}