{"nodes":[{"id":"2050494","x":3361206.2,"y":16336184.9,"majorLevel":null,"majorInt":"N","eligible":true,"outsideGa":true},{"id":"2050497","x":3362090.0,"y":16364669.7,"majorLevel":null,"majorInt":"N","eligible":true,"outsideGa":true},{"id":"2050498","x":3362197.9,"y":16334208.7,"majorLevel":null,"majorInt":"N","eligible":true,"outsideGa":true},{"id":"2050501","x":3362953.0,"y":16365095.5,"majorLevel":null,"majorInt":"N","eligible":true,"outsideGa":true},{"id":"2050503","x":3363155.9,"y":16365238.2,"majorLevel":null,"majorInt":"N","eligible":true,"outsideGa":true},{"id":"2050504","x":3363222.5,"y":16387882.9,"majorLevel":null,"majorInt":"N","eligible":true,"outsideGa":true},{"id":"2050506","x":3363306.6,"y":16386487.0,"majorLevel":null,"majorInt":"N","eligible":true,"outsideGa":true},{"id":"2050507","x":3363324.1,"y":16388569.2,"majorLevel":null,"majorInt":"N","eligible":true,"outsideGa":true},{"id":"2050508","x":3363686.9,"y":16365668.6,"majorLevel":null,"majorInt":"N","eligible":true,"outsideGa":true},{"id":"2050509","x":3363742.8,"y":16389780.5,"majorLevel":null,"majorInt":"N","eligible":true,"outsideGa":true},{"id":"2050511","x":3364334.7,"y":16331617.6,"majorLevel":null,"majorInt":"N","eligible":true,"outsideGa":true},{"id":"2050513","x":3364716.1,"y":16366748.0,"majorLevel":null,"majorInt":"N","eligible":true,"outsideGa":true},{"id":"2050514","x":3365190.9,"y":16373671.7,"majorLevel":null,"majorInt":"N","eligible":true,"outsideGa":true},{"id":"2050515","x":3365243.9,"y":16368014.7,"majorLevel":null,"majorInt":"N","eligible":true,"outsideGa":true},{"id":"2050517","x":3365341.4,"y":16369221.6,"majorLevel":null,"majorInt":"N","eligible":true,"outsideGa":true},{"id":"2050518","x":3365375.9,"y":16374739.2,"majorLevel":null,"majorInt":"N","eligible":true,"outsideGa":true},{"id":"2050519","x":3365458.9,"y":16375517.2,"majorLevel":null,"majorInt":"N","eligible":true,"outsideGa":true},{"id":"2050521","x":3365637.0,"y":16330092.1,"majorLevel":null,"majorInt":"N","eligible":true,"outsideGa":true},{"id":"2050528","x":3366913.3,"y":16328414.3,"majorLevel":null,"majorInt":"N","eligible":true,"outsideGa":true},{"id":"2050530","x":3367092.5,"y":16394821.4,"majorLevel":null,"majorInt":"N","eligible":true,"outsideGa":true},{"id":"2050534","x":3367485.5,"y":16396579.5,"majorLevel":null,"majorInt":"N","eligible":true,"outsideGa":true},{"id":"2050535","x":3367616.6,"y":16398042.6,"majorLevel":null,"majorInt":"N","eligible":true,"outsideGa":true},{"id":"2050720","x":3410618.0,"y":16371418.3,"majorLevel":null,"majorInt":"N","eligible":true,"outsideGa":true},{"id":"2050721","x":3410749.1,"y":16372419.8,"majorLevel":null,"majorInt":"N","eligible":true,"outsideGa":true},{"id":"2050722","x":3410891.6,"y":16373285.9,"majorLevel":null,"majorInt":"N","eligible":true,"outsideGa":true},{"id":"2050730","x":3412216.0,"y":16380147.7,"majorLevel":null,"majorInt":"N","eligible":true,"outsideGa":true},{"id":"2050731","x":3412626.3,"y":16382230.8,"majorLevel":null,"majorInt":"N","eligible":true,"outsideGa":true},{"id":"2050733","x":3412981.0,"y":16384079.6,"majorLevel":null,"majorInt":"N","eligible":true,"outsideGa":true},{"id":"2050738","x":3414910.8,"y":16322313.8,"majorLevel":null,"majorInt":"N","eligible":true,"outsideGa":true},{"id":"2050739","x":3415446.9,"y":16396727.1,"majorLevel":null,"majorInt":"N","eligible":true,"outsideGa":true},{"id":"2050742","x":3415838.2,"y":16325696.0,"majorLevel":null,"majorInt":"N","eligible":true,"outsideGa":true},{"id":"2050745","x":3416555.0,"y":16327026.0,"majorLevel":null,"majorInt":"N","eligible":true,"outsideGa":true},{"id":"2050746","x":3416697.9,"y":16342123.3,"majorLevel":null,"majorInt":"N","eligible":true,"outsideGa":true},{"id":"2050748","x":3416988.7,"y":16329088.2,"majorLevel":null,"majorInt":"N","eligible":true,"outsideGa":true},{"id":"2050750","x":3417169.7,"y":16341370.1,"majorLevel":null,"majorInt":"N","eligible":true,"outsideGa":true},{"id":"2050753","x":3417631.6,"y":16340579.7,"majorLevel":null,"majorInt":"N","eligible":true,"outsideGa":true},{"id":"2050754","x":3417772.1,"y":16334700.5,"majorLevel":null,"majorInt":"N","eligible":true,"outsideGa":true},{"id":"2050756","x":3418147.5,"y":16335549.8,"majorLevel":null,"majorInt":"N","eligible":true,"outsideGa":true},{"id":"2050757","x":3418289.6,"y":16339288.1,"majorLevel":null,"majorInt":"N","eligible":true,"outsideGa":true},{"id":"2050758","x":3418443.4,"y":16336376.6,"majorLevel":null,"majorInt":"N","eligible":true,"outsideGa":true},{"id":"2050759","x":3418529.2,"y":16337826.1,"majorLevel":null,"majorInt":"N","eligible":true,"outsideGa":true}]}