{"nodes":[{"id":"2039169","x":320859.0,"y":13283323.0,"majorLevel":null,"majorInt":"N","eligible":true,"outsideGa":true},{"id":"2039171","x":321048.2,"y":13284633.1,"majorLevel":null,"majorInt":"N","eligible":true,"outsideGa":true},{"id":"2039174","x":321596.5,"y":13348715.0,"majorLevel":null,"majorInt":"N","eligible":true,"outsideGa":true},{"id":"2039176","x":321837.8,"y":13283935.2,"majorLevel":null,"majorInt":"N","eligible":true,"outsideGa":true},{"id":"2039180","x":322072.8,"y":13349561.4,"majorLevel":null,"majorInt":"N","eligible":true,"outsideGa":true},{"id":"2039185","x":322623.5,"y":13283343.5,"majorLevel":null,"majorInt":"N","eligible":true,"outsideGa":true},{"id":"2039186","x":322728.6,"y":13284669.8,"majorLevel":null,"majorInt":"N","eligible":true,"outsideGa":true},{"id":"2039192","x":323663.7,"y":13348700.1,"majorLevel":null,"majorInt":"N","eligible":true,"outsideGa":true},{"id":"2039194","x":323893.8,"y":13280061.2,"majorLevel":null,"majorInt":"N","eligible":true,"outsideGa":true},{"id":"2039197","x":324722.7,"y":13280852.8,"majorLevel":null,"majorInt":"N","eligible":true,"outsideGa":true},{"id":"2039198","x":324753.7,"y":13359008.3,"majorLevel":null,"majorInt":"N","eligible":true,"outsideGa":true},{"id":"2039203","x":325132.8,"y":13280106.2,"majorLevel":null,"majorInt":"N","eligible":true,"outsideGa":true},{"id":"2039205","x":325308.5,"y":13290910.8,"majorLevel":null,"majorInt":"N","eligible":true,"outsideGa":true},{"id":"2039211","x":326233.3,"y":13280258.8,"majorLevel":null,"majorInt":"N","eligible":true,"outsideGa":true},{"id":"2039219","x":328050.6,"y":13316326.8,"majorLevel":null,"majorInt":"N","eligible":true,"outsideGa":true},{"id":"2039226","x":328691.9,"y":13316683.4,"majorLevel":null,"majorInt":"N","eligible":true,"outsideGa":true},{"id":"2039230","x":329365.8,"y":13303855.7,"majorLevel":null,"majorInt":"N","eligible":true,"outsideGa":true},{"id":"2039234","x":329887.0,"y":13303067.8,"majorLevel":null,"majorInt":"N","eligible":true,"outsideGa":true},{"id":"2039240","x":331710.6,"y":13302125.6,"majorLevel":null,"majorInt":"N","eligible":true,"outsideGa":true},{"id":"2039242","x":331864.0,"y":13302545.2,"majorLevel":null,"majorInt":"N","eligible":true,"outsideGa":true},{"id":"2039246","x":332295.8,"y":13302211.1,"majorLevel":null,"majorInt":"N","eligible":true,"outsideGa":true},{"id":"2039262","x":334288.2,"y":13302781.9,"majorLevel":null,"majorInt":"N","eligible":true,"outsideGa":true},{"id":"2039265","x":334541.9,"y":13305079.1,"majorLevel":null,"majorInt":"N","eligible":true,"outsideGa":true},{"id":"2039266","x":334563.9,"y":13303274.5,"majorLevel":null,"majorInt":"N","eligible":true,"outsideGa":true},{"id":"2039269","x":334860.5,"y":13302956.1,"majorLevel":null,"majorInt":"N","eligible":true,"outsideGa":true},{"id":"2039270","x":335156.8,"y":13281789.6,"majorLevel":null,"majorInt":"N","eligible":true,"outsideGa":true},{"id":"2039272","x":335259.2,"y":13302631.9,"majorLevel":null,"majorInt":"N","eligible":true,"outsideGa":true},{"id":"2039273","x":335391.9,"y":13303085.5,"majorLevel":null,"majorInt":"N","eligible":true,"outsideGa":true},{"id":"2039282","x":336032.8,"y":13281919.7,"majorLevel":null,"majorInt":"N","eligible":true,"outsideGa":true},{"id":"2039283","x":336327.8,"y":13282698.4,"majorLevel":null,"majorInt":"N","eligible":true,"outsideGa":true},{"id":"2039290","x":336942.3,"y":13282161.3,"majorLevel":null,"majorInt":"N","eligible":true,"outsideGa":true},{"id":"2039332","x":341407.5,"y":13299249.5,"majorLevel":null,"majorInt":"N","eligible":true,"outsideGa":true},{"id":"2039333","x":341506.3,"y":13311946.8,"majorLevel":null,"majorInt":"N","eligible":true,"outsideGa":true},{"id":"2039337","x":342089.2,"y":13304197.7,"majorLevel":null,"majorInt":"N","eligible":true,"outsideGa":true},{"id":"2039338","x":342252.0,"y":13311999.3,"majorLevel":null,"majorInt":"N","eligible":true,"outsideGa":true},{"id":"2039339","x":342268.0,"y":13312654.8,"majorLevel":null,"majorInt":"N","eligible":true,"outsideGa":true},{"id":"2039354","x":343077.8,"y":13303621.1,"majorLevel":null,"majorInt":"N","eligible":true,"outsideGa":true},{"id":"2039356","x":343188.5,"y":13305540.0,"majorLevel":null,"majorInt":"N","eligible":true,"outsideGa":true},{"id":"2039357","x":343255.4,"y":13304764.1,"majorLevel":null,"majorInt":"N","eligible":true,"outsideGa":true},{"id":"2039363","x":344365.6,"y":13304845.0,"majorLevel":null,"majorInt":"N","eligible":true,"outsideGa":true},{"id":"2039391","x":348401.2,"y":13288334.4,"majorLevel":null,"majorInt":"N","eligible":true,"outsideGa":true},{"id":"2039395","x":348737.1,"y":13289329.5,"majorLevel":null,"majorInt":"N","eligible":true,"outsideGa":true},{"id":"2039397","x":349223.9,"y":13288641.6,"majorLevel":null,"majorInt":"N","eligible":true,"outsideGa":true},{"id":"2039398","x":349769.4,"y":13287914.7,"majorLevel":null,"majorInt":"N","eligible":true,"outsideGa":true},{"id":"2039399","x":350174.7,"y":13288898.2,"majorLevel":null,"majorInt":"N","eligible":true,"outsideGa":true},{"id":"2039400","x":350391.9,"y":13321726.6,"majorLevel":null,"majorInt":"N","eligible":true,"outsideGa":true},{"id":"2039447","x":359354.7,"y":13296193.6,"majorLevel":null,"majorInt":"N","eligible":true,"outsideGa":true},{"id":"2039448","x":359542.9,"y":13294582.8,"majorLevel":null,"majorInt":"N","eligible":true,"outsideGa":true},{"id":"2039455","x":360858.9,"y":13295570.2,"majorLevel":null,"majorInt":"N","eligible":true,"outsideGa":true},{"id":"2039461","x":362047.1,"y":13294422.0,"majorLevel":null,"majorInt":"N","eligible":true,"outsideGa":true},{"id":"2039462","x":362235.1,"y":13296597.8,"majorLevel":null,"majorInt":"N","eligible":true,"outsideGa":true},{"id":"2039463","x":362595.2,"y":13293116.0,"majorLevel":null,"majorInt":"N","eligible":true,"outsideGa":true},{"id":"2039466","x":362781.2,"y":13292296.4,"majorLevel":null,"majorInt":"N","eligible":true,"outsideGa":true},{"id":"2039467","x":362907.6,"y":13291372.7,"majorLevel":null,"majorInt":"N","eligible":true,"outsideGa":true},{"id":"2039469","x":362957.2,"y":13297133.2,"majorLevel":null,"majorInt":"N","eligible":true,"outsideGa":true},{"id":"2039470","x":363202.0,"y":13297336.3,"majorLevel":null,"majorInt":"N","eligible":true,"outsideGa":true},{"id":"2039473","x":363724.1,"y":13292018.8,"majorLevel":null,"majorInt":"N","eligible":true,"outsideGa":true},{"id":"2039487","x":364916.1,"y":13298642.0,"majorLevel":null,"majorInt":"N","eligible":true,"outsideGa":true},{"id":"2039499","x":367164.4,"y":13291005.2,"majorLevel":null,"majorInt":"N","eligible":true,"outsideGa":true},{"id":"2039541","x":372822.6,"y":13335849.6,"majorLevel":null,"majorInt":"N","eligible":true,"outsideGa":true},{"id":"2039573","x":378792.3,"y":13324550.6,"majorLevel":null,"majorInt":"N","eligible":true,"outsideGa":true},{"id":"2039602","x":381689.8,"y":13334376.4,"majorLevel":null,"majorInt":"N","eligible":true,"outsideGa":true},{"id":"2039603","x":381705.8,"y":13309620.1,"majorLevel":null,"majorInt":"N","eligible":true,"outsideGa":true},{"id":"2039605","x":382372.2,"y":13337934.1,"majorLevel":null,"majorInt":"N","eligible":true,"outsideGa":true},{"id":"2039606","x":382378.2,"y":13309956.6,"majorLevel":null,"majorInt":"N","eligible":true,"outsideGa":true},{"id":"2039607","x":382444.1,"y":13311507.5,"majorLevel":null,"majorInt":"N","eligible":true,"outsideGa":true},{"id":"2039608","x":382542.2,"y":13311133.6,"majorLevel":null,"majorInt":"N","eligible":true,"outsideGa":true},{"id":"2039609","x":382755.2,"y":13310196.8,"majorLevel":null,"majorInt":"N","eligible":true,"outsideGa":true},{"id":"2039614","x":383127.8,"y":13337875.2,"majorLevel":null,"majorInt":"N","eligible":true,"outsideGa":true},{"id":"2039617","x":383787.7,"y":13310797.7,"majorLevel":null,"majorInt":"N","eligible":true,"outsideGa":true},{"id":"2039647","x":389405.1,"y":13338003.1,"majorLevel":null,"majorInt":"N","eligible":true,"outsideGa":true}]}