{"nodes":[{"id":"2040058","x":463158.9,"y":15678530.5,"majorLevel":null,"majorInt":"N","eligible":true,"outsideGa":true},{"id":"2040068","x":464264.5,"y":15678139.0,"majorLevel":null,"majorInt":"N","eligible":true,"outsideGa":true},{"id":"2040092","x":466902.2,"y":15678818.0,"majorLevel":null,"majorInt":"N","eligible":true,"outsideGa":true},{"id":"2040100","x":467386.0,"y":15675049.0,"majorLevel":null,"majorInt":"N","eligible":true,"outsideGa":true},{"id":"2040101","x":467482.1,"y":15674300.0,"majorLevel":null,"majorInt":"N","eligible":true,"outsideGa":true},{"id":"2040113","x":468663.1,"y":15674555.4,"majorLevel":null,"majorInt":"N","eligible":true,"outsideGa":true},{"id":"2040114","x":468663.5,"y":15669110.5,"majorLevel":null,"majorInt":"N","eligible":true,"outsideGa":true},{"id":"2040118","x":469008.4,"y":15667811.4,"majorLevel":null,"majorInt":"N","eligible":true,"outsideGa":true},{"id":"2040120","x":469303.5,"y":15666797.4,"majorLevel":null,"majorInt":"N","eligible":true,"outsideGa":true},{"id":"2040136","x":470589.1,"y":15654227.2,"majorLevel":null,"majorInt":"N","eligible":true,"outsideGa":true},{"id":"2040162","x":474191.4,"y":15601175.1,"majorLevel":null,"majorInt":"N","eligible":true,"outsideGa":true},{"id":"2040164","x":474481.4,"y":15631962.1,"majorLevel":null,"majorInt":"N","eligible":true,"outsideGa":true},{"id":"2040167","x":474766.2,"y":15602756.0,"majorLevel":null,"majorInt":"N","eligible":true,"outsideGa":true},{"id":"2040170","x":475131.6,"y":15604005.5,"majorLevel":null,"majorInt":"N","eligible":true,"outsideGa":true},{"id":"2040178","x":476190.7,"y":15671620.7,"majorLevel":null,"majorInt":"N","eligible":true,"outsideGa":true},{"id":"2040182","x":476802.2,"y":15609891.5,"majorLevel":null,"majorInt":"N","eligible":true,"outsideGa":true},{"id":"2040187","x":477003.8,"y":15613485.5,"majorLevel":null,"majorInt":"N","eligible":true,"outsideGa":true},{"id":"2040188","x":477056.1,"y":15612304.9,"majorLevel":null,"majorInt":"N","eligible":true,"outsideGa":true}]}