{"nodes":[{"id":"20115","x":488515.8,"y":11979383.9,"majorLevel":2.0,"majorInt":"Y","eligible":false},{"id":"20116","x":488535.6,"y":11979315.1,"majorLevel":2.0,"majorInt":"Y","eligible":false},{"id":"20117","x":483223.5,"y":11978407.4,"majorLevel":2.0,"majorInt":"Y","eligible":false},{"id":"20118","x":483233.9,"y":11978338.4,"majorLevel":2.0,"majorInt":"Y","eligible":false},{"id":"152519","x":506973.7,"y":11938893.8,"majorLevel":4.0,"majorInt":"N","eligible":true},{"id":"152548","x":498448.4,"y":11980769.4,"majorLevel":2.0,"majorInt":"Y","eligible":false},{"id":"152549","x":498934.9,"y":11980856.8,"majorLevel":2.0,"majorInt":"Y","eligible":false},{"id":"152550","x":498927.6,"y":11980925.8,"majorLevel":2.0,"majorInt":"Y","eligible":false},{"id":"152551","x":499507.6,"y":11981032.8,"majorLevel":2.0,"majorInt":"Y","eligible":false},{"id":"152561","x":514458.2,"y":11956295.8,"majorLevel":4.0,"majorInt":"N","eligible":true},{"id":"152562","x":514464.4,"y":11956899.8,"majorLevel":4.0,"majorInt":"N","eligible":true},{"id":"152564","x":515264.9,"y":11964160.0,"majorLevel":4.0,"majorInt":"N","eligible":true},{"id":"152565","x":532384.1,"y":11945937.2,"majorLevel":4.0,"majorInt":"N","eligible":true},{"id":"152567","x":535248.6,"y":11944378.9,"majorLevel":4.0,"majorInt":"N","eligible":true},{"id":"152568","x":534199.3,"y":11954869.8,"majorLevel":4.0,"majorInt":"N","eligible":true},{"id":"152569","x":534718.7,"y":11956424.6,"majorLevel":4.0,"majorInt":"N","eligible":true},{"id":"152570","x":531788.3,"y":11966805.1,"majorLevel":4.0,"majorInt":"N","eligible":true},{"id":"152572","x":535395.5,"y":11959844.8,"majorLevel":4.0,"majorInt":"N","eligible":true},{"id":"152573","x":534710.2,"y":11962940.9,"majorLevel":4.0,"majorInt":"N","eligible":true},{"id":"152576","x":554637.8,"y":11923740.3,"majorLevel":4.0,"majorInt":"N","eligible":true},{"id":"152578","x":554999.2,"y":11938038.7,"majorLevel":4.0,"majorInt":"N","eligible":true},{"id":"152579","x":555415.9,"y":11938027.5,"majorLevel":4.0,"majorInt":"N","eligible":true},{"id":"152580","x":555441.0,"y":11938395.5,"majorLevel":4.0,"majorInt":"N","eligible":true},{"id":"152581","x":555719.0,"y":11939178.8,"majorLevel":4.0,"majorInt":"N","eligible":true},{"id":"152584","x":516511.2,"y":11975691.4,"majorLevel":4.0,"majorInt":"N","eligible":true},{"id":"152585","x":515012.2,"y":11981562.1,"majorLevel":4.0,"majorInt":"N","eligible":true},{"id":"152586","x":513164.9,"y":11983527.1,"majorLevel":2.0,"majorInt":"Y","eligible":false},{"id":"152587","x":514935.8,"y":11983856.7,"majorLevel":2.0,"majorInt":"Y","eligible":false},{"id":"152588","x":514952.5,"y":11984388.1,"majorLevel":4.0,"majorInt":"N","eligible":true},{"id":"152589","x":516924.3,"y":11983065.5,"majorLevel":4.0,"majorInt":"N","eligible":true},{"id":"152590","x":516744.1,"y":11984186.9,"majorLevel":2.0,"majorInt":"Y","eligible":false},{"id":"152591","x":518424.6,"y":11984493.4,"majorLevel":2.0,"majorInt":"Y","eligible":false},{"id":"152593","x":532379.4,"y":11986603.8,"majorLevel":2.0,"majorInt":"Y","eligible":false},{"id":"152594","x":532362.7,"y":11986672.7,"majorLevel":2.0,"majorInt":"Y","eligible":false},{"id":"152595","x":533355.5,"y":11986761.5,"majorLevel":2.0,"majorInt":"Y","eligible":false},{"id":"152596","x":535424.0,"y":11987031.4,"majorLevel":2.0,"majorInt":"Y","eligible":false},{"id":"152599","x":543710.1,"y":11987923.7,"majorLevel":2.0,"majorInt":"Y","eligible":false},{"id":"152600","x":543724.5,"y":11988000.3,"majorLevel":2.0,"majorInt":"Y","eligible":false},{"id":"152601","x":544492.5,"y":11991665.9,"majorLevel":4.0,"majorInt":"N","eligible":true},{"id":"160510","x":499552.3,"y":11980971.6,"majorLevel":2.0,"majorInt":"Y","eligible":false},{"id":"357785","x":506503.2,"y":11926683.1,"majorLevel":4.0,"majorInt":"N","eligible":true},{"id":"357788","x":507849.9,"y":11925670.4,"majorLevel":4.0,"majorInt":"N","eligible":true},{"id":"357789","x":513453.5,"y":11921430.7,"majorLevel":4.0,"majorInt":"N","eligible":true},{"id":"357791","x":506354.9,"y":11929617.1,"majorLevel":4.0,"majorInt":"N","eligible":true},{"id":"357792","x":506378.3,"y":11929930.3,"majorLevel":4.0,"majorInt":"N","eligible":true},{"id":"357796","x":506739.5,"y":11935379.1,"majorLevel":4.0,"majorInt":"N","eligible":true},{"id":"357797","x":506760.8,"y":11935826.9,"majorLevel":4.0,"majorInt":"N","eligible":true},{"id":"357798","x":506877.7,"y":11937800.8,"majorLevel":4.0,"majorInt":"N","eligible":true},{"id":"357809","x":510862.8,"y":11946157.9,"majorLevel":4.0,"majorInt":"N","eligible":true},{"id":"358025","x":491286.1,"y":11979825.2,"majorLevel":2.0,"majorInt":"Y","eligible":false},{"id":"358026","x":491291.3,"y":11979898.1,"majorLevel":2.0,"majorInt":"Y","eligible":false},{"id":"358027","x":493459.7,"y":11980225.1,"majorLevel":2.0,"majorInt":"Y","eligible":false},{"id":"358028","x":493461.8,"y":11980294.3,"majorLevel":2.0,"majorInt":"Y","eligible":false},{"id":"358030","x":498447.4,"y":11980838.5,"majorLevel":2.0,"majorInt":"Y","eligible":false},{"id":"358037","x":502729.7,"y":11981558.3,"majorLevel":2.0,"majorInt":"Y","eligible":false},{"id":"358038","x":502734.9,"y":11981627.5,"majorLevel":2.0,"majorInt":"Y","eligible":false},{"id":"358080","x":514459.7,"y":11956597.8,"majorLevel":4.0,"majorInt":"N","eligible":true},{"id":"358081","x":514471.4,"y":11957256.5,"majorLevel":4.0,"majorInt":"N","eligible":true},{"id":"358083","x":514475.5,"y":11957594.9,"majorLevel":4.0,"majorInt":"N","eligible":true},{"id":"358084","x":514485.6,"y":11957948.0,"majorLevel":4.0,"majorInt":"N","eligible":true},{"id":"358085","x":514492.9,"y":11958286.5,"majorLevel":4.0,"majorInt":"N","eligible":true},{"id":"358086","x":515347.2,"y":11969713.5,"majorLevel":4.0,"majorInt":"N","eligible":true},{"id":"358093","x":532403.1,"y":11950976.8,"majorLevel":4.0,"majorInt":"N","eligible":true},{"id":"358097","x":526672.5,"y":11969411.9,"majorLevel":4.0,"majorInt":"N","eligible":true},{"id":"358098","x":525912.1,"y":11971197.1,"majorLevel":4.0,"majorInt":"N","eligible":true},{"id":"358099","x":534996.9,"y":11961661.2,"majorLevel":4.0,"majorInt":"N","eligible":true},{"id":"358100","x":534686.6,"y":11963046.1,"majorLevel":4.0,"majorInt":"N","eligible":true},{"id":"358108","x":549415.2,"y":11939804.8,"majorLevel":4.0,"majorInt":"N","eligible":true},{"id":"358122","x":554701.3,"y":11925371.4,"majorLevel":4.0,"majorInt":"N","eligible":true},{"id":"358130","x":554969.8,"y":11929716.8,"majorLevel":4.0,"majorInt":"N","eligible":true},{"id":"358131","x":555012.7,"y":11930336.1,"majorLevel":4.0,"majorInt":"N","eligible":true},{"id":"358139","x":553614.4,"y":11938091.9,"majorLevel":4.0,"majorInt":"N","eligible":true},{"id":"358140","x":554194.1,"y":11938065.3,"majorLevel":4.0,"majorInt":"N","eligible":true},{"id":"358146","x":554570.0,"y":11938057.0,"majorLevel":4.0,"majorInt":"N","eligible":true},{"id":"358148","x":554927.2,"y":11938041.2,"majorLevel":4.0,"majorInt":"N","eligible":true},{"id":"358153","x":555394.1,"y":11937274.0,"majorLevel":4.0,"majorInt":"N","eligible":true},{"id":"358155","x":555406.5,"y":11937652.6,"majorLevel":4.0,"majorInt":"N","eligible":true},{"id":"358156","x":555788.7,"y":11938012.0,"majorLevel":4.0,"majorInt":"N","eligible":true},{"id":"358160","x":556149.0,"y":11937999.8,"majorLevel":4.0,"majorInt":"N","eligible":true},{"id":"358166","x":557056.0,"y":11937880.5,"majorLevel":4.0,"majorInt":"N","eligible":true},{"id":"358167","x":557176.0,"y":11937817.0,"majorLevel":4.0,"majorInt":"N","eligible":true},{"id":"358214","x":516244.9,"y":11976720.5,"majorLevel":4.0,"majorInt":"N","eligible":true},{"id":"358215","x":514954.7,"y":11984450.0,"majorLevel":4.0,"majorInt":"N","eligible":true},{"id":"358216","x":516906.4,"y":11984804.3,"majorLevel":5.0,"majorInt":"N","eligible":true},{"id":"358217","x":517910.1,"y":11984401.7,"majorLevel":2.0,"majorInt":"Y","eligible":false},{"id":"358221","x":521019.0,"y":11979189.5,"majorLevel":4.0,"majorInt":"N","eligible":true},{"id":"358222","x":525229.4,"y":11972823.6,"majorLevel":4.0,"majorInt":"N","eligible":true},{"id":"358223","x":515747.8,"y":11989523.3,"majorLevel":4.0,"majorInt":"N","eligible":true},{"id":"358225","x":515966.6,"y":11991520.5,"majorLevel":4.0,"majorInt":"N","eligible":true},{"id":"358227","x":516529.9,"y":11996877.7,"majorLevel":4.0,"majorInt":"N","eligible":true},{"id":"358228","x":516617.2,"y":11997686.7,"majorLevel":4.0,"majorInt":"N","eligible":true},{"id":"358236","x":530728.5,"y":11986413.5,"majorLevel":2.0,"majorInt":"Y","eligible":false},{"id":"358237","x":530686.9,"y":11986478.3,"majorLevel":2.0,"majorInt":"Y","eligible":false},{"id":"358238","x":531046.9,"y":11986447.7,"majorLevel":2.0,"majorInt":"Y","eligible":false},{"id":"358239","x":530995.8,"y":11986516.0,"majorLevel":2.0,"majorInt":"Y","eligible":false},{"id":"358245","x":534329.1,"y":11986871.8,"majorLevel":2.0,"majorInt":"Y","eligible":false},{"id":"358246","x":534762.9,"y":11986922.5,"majorLevel":2.0,"majorInt":"Y","eligible":false},{"id":"358249","x":536269.6,"y":11987132.5,"majorLevel":2.0,"majorInt":"Y","eligible":false},{"id":"358251","x":537112.2,"y":11987229.9,"majorLevel":2.0,"majorInt":"Y","eligible":false},{"id":"358294","x":538903.8,"y":11987408.2,"majorLevel":2.0,"majorInt":"Y","eligible":false},{"id":"358305","x":551018.9,"y":11986287.5,"majorLevel":2.0,"majorInt":"Y","eligible":false},{"id":"358306","x":551058.7,"y":11986339.1,"majorLevel":2.0,"majorInt":"Y","eligible":false},{"id":"358307","x":540498.5,"y":11987590.8,"majorLevel":2.0,"majorInt":"Y","eligible":false},{"id":"358308","x":543801.0,"y":11988289.0,"majorLevel":4.0,"majorInt":"N","eligible":true},{"id":"358309","x":549149.3,"y":11987595.3,"majorLevel":2.0,"majorInt":"Y","eligible":false},{"id":"358310","x":549173.3,"y":11987653.9,"majorLevel":2.0,"majorInt":"Y","eligible":false},{"id":"358311","x":545330.4,"y":11996013.0,"majorLevel":4.0,"majorInt":"N","eligible":true},{"id":"358312","x":545516.0,"y":11996882.0,"majorLevel":4.0,"majorInt":"N","eligible":true},{"id":"358317","x":553688.9,"y":11984429.3,"majorLevel":2.0,"majorInt":"Y","eligible":false},{"id":"358318","x":553728.7,"y":11984477.3,"majorLevel":2.0,"majorInt":"Y","eligible":false},{"id":"358319","x":554277.4,"y":11984017.1,"majorLevel":2.0,"majorInt":"Y","eligible":false},{"id":"358320","x":554301.3,"y":11984083.0,"majorLevel":2.0,"majorInt":"Y","eligible":false},{"id":"412236","x":533645.7,"y":11986795.3,"majorLevel":2.0,"majorInt":"Y","eligible":false},{"id":"412238","x":514965.9,"y":11983529.7,"majorLevel":4.0,"majorInt":"N","eligible":true},{"id":"412241","x":515914.8,"y":11972225.6,"majorLevel":4.0,"majorInt":"N","eligible":true},{"id":"412242","x":541728.0,"y":11987727.3,"majorLevel":2.0,"majorInt":"Y","eligible":false},{"id":"412243","x":537980.1,"y":11987305.8,"majorLevel":2.0,"majorInt":"Y","eligible":false},{"id":"413904","x":555518.8,"y":11938797.0,"majorLevel":4.0,"majorInt":"N","eligible":true},{"id":"417446","x":534812.1,"y":11956644.4,"majorLevel":4.0,"majorInt":"N","eligible":true},{"id":"420263","x":545783.4,"y":11998290.8,"majorLevel":4.0,"majorInt":"N","eligible":true},{"id":"432456","x":558111.9,"y":11939877.7,"majorLevel":4.0,"majorInt":"N","eligible":true},{"id":"432464","x":554714.7,"y":11925691.9,"majorLevel":4.0,"majorInt":"N","eligible":true},{"id":"464428","x":555249.9,"y":11932992.6,"majorLevel":4.0,"majorInt":"N","eligible":true},{"id":"470446","x":514939.4,"y":11962361.2,"majorLevel":4.0,"majorInt":"N","eligible":true},{"id":"470447","x":514907.7,"y":11962186.1,"majorLevel":4.0,"majorInt":"N","eligible":true},{"id":"470448","x":514884.8,"y":11962051.1,"majorLevel":4.0,"majorInt":"N","eligible":true},{"id":"470449","x":514867.5,"y":11961956.2,"majorLevel":4.0,"majorInt":"N","eligible":true},{"id":"470455","x":514504.6,"y":11958938.0,"majorLevel":4.0,"majorInt":"N","eligible":true},{"id":"470494","x":509542.8,"y":11982808.8,"majorLevel":2.0,"majorInt":"Y","eligible":false},{"id":"470495","x":509541.6,"y":11982881.6,"majorLevel":2.0,"majorInt":"Y","eligible":false},{"id":"470525","x":514951.4,"y":11983056.5,"majorLevel":4.0,"majorInt":"N","eligible":true},{"id":"470820","x":516531.3,"y":11986199.2,"majorLevel":5.0,"majorInt":"N","eligible":true},{"id":"470855","x":516274.5,"y":11994421.4,"majorLevel":4.0,"majorInt":"N","eligible":true},{"id":"470954","x":545676.8,"y":11997743.3,"majorLevel":4.0,"majorInt":"N","eligible":true},{"id":"471490","x":515794.4,"y":11989938.8,"majorLevel":4.0,"majorInt":"N","eligible":true},{"id":"471509","x":516052.2,"y":11988647.6,"majorLevel":5.0,"majorInt":"N","eligible":true},{"id":"492392","x":558616.4,"y":11981859.9,"majorLevel":2.0,"majorInt":"Y","eligible":false},{"id":"492393","x":558646.8,"y":11981911.3,"majorLevel":2.0,"majorInt":"Y","eligible":false},{"id":"499151","x":527586.4,"y":11968207.6,"majorLevel":4.0,"majorInt":"N","eligible":true},{"id":"499152","x":515156.6,"y":11963481.6,"majorLevel":4.0,"majorInt":"N","eligible":true},{"id":"499153","x":534382.5,"y":11964052.6,"majorLevel":4.0,"majorInt":"N","eligible":true},{"id":"499156","x":543897.8,"y":11988676.2,"majorLevel":4.0,"majorInt":"N","eligible":true},{"id":"499333","x":516625.8,"y":11984756.3,"majorLevel":5.0,"majorInt":"N","eligible":true},{"id":"499334","x":515627.4,"y":11988422.7,"majorLevel":4.0,"majorInt":"N","eligible":true},{"id":"499336","x":515846.2,"y":11990427.2,"majorLevel":4.0,"majorInt":"N","eligible":true},{"id":"499337","x":516037.9,"y":11992158.4,"majorLevel":4.0,"majorInt":"N","eligible":true},{"id":"499338","x":516157.4,"y":11993317.2,"majorLevel":4.0,"majorInt":"N","eligible":true},{"id":"499569","x":530105.9,"y":11967349.3,"majorLevel":4.0,"majorInt":"N","eligible":true},{"id":"499575","x":515421.9,"y":11979956.7,"majorLevel":4.0,"majorInt":"N","eligible":true},{"id":"499576","x":517932.7,"y":11981767.8,"majorLevel":4.0,"majorInt":"N","eligible":true},{"id":"499577","x":517413.0,"y":11982207.2,"majorLevel":4.0,"majorInt":"N","eligible":true},{"id":"503081","x":522448.2,"y":11978000.5,"majorLevel":4.0,"majorInt":"N","eligible":true},{"id":"503091","x":515023.6,"y":11962781.0,"majorLevel":4.0,"majorInt":"N","eligible":true},{"id":"503093","x":514415.0,"y":11955247.2,"majorLevel":4.0,"majorInt":"N","eligible":true},{"id":"503151","x":502111.3,"y":11981512.5,"majorLevel":2.0,"majorInt":"Y","eligible":false},{"id":"503152","x":502112.4,"y":11981443.4,"majorLevel":2.0,"majorInt":"Y","eligible":false},{"id":"503585","x":516636.1,"y":11984698.2,"majorLevel":5.0,"majorInt":"N","eligible":true},{"id":"517310","x":532394.8,"y":11950911.2,"majorLevel":4.0,"majorInt":"N","eligible":true},{"id":"517393","x":555392.8,"y":11936975.6,"majorLevel":4.0,"majorInt":"N","eligible":true},{"id":"517395","x":555399.7,"y":11937496.0,"majorLevel":4.0,"majorInt":"N","eligible":true},{"id":"517436","x":506922.5,"y":11938554.6,"majorLevel":4.0,"majorInt":"N","eligible":true},{"id":"517558","x":506272.1,"y":11927250.8,"majorLevel":4.0,"majorInt":"N","eligible":true},{"id":"553933","x":544405.0,"y":11988062.4,"majorLevel":2.0,"majorInt":"Y","eligible":false},{"id":"554418","x":481277.4,"y":11978047.9,"majorLevel":2.0,"majorInt":"Y","eligible":false},{"id":"554419","x":481287.8,"y":11977978.9,"majorLevel":2.0,"majorInt":"Y","eligible":false},{"id":"554420","x":504934.3,"y":11981963.1,"majorLevel":2.0,"majorInt":"Y","eligible":false},{"id":"554421","x":504933.2,"y":11982032.2,"majorLevel":2.0,"majorInt":"Y","eligible":false},{"id":"554423","x":507506.7,"y":11982435.5,"majorLevel":2.0,"majorInt":"Y","eligible":false},{"id":"554424","x":507583.6,"y":11982520.3,"majorLevel":2.0,"majorInt":"Y","eligible":false},{"id":"554425","x":507932.8,"y":11982583.9,"majorLevel":2.0,"majorInt":"Y","eligible":false},{"id":"554426","x":507949.4,"y":11982518.7,"majorLevel":2.0,"majorInt":"Y","eligible":false},{"id":"554427","x":512997.1,"y":11983462.7,"majorLevel":2.0,"majorInt":"Y","eligible":false},{"id":"554428","x":512697.0,"y":11983458.0,"majorLevel":2.0,"majorInt":"Y","eligible":false},{"id":"554430","x":513423.8,"y":11983571.2,"majorLevel":2.0,"majorInt":"Y","eligible":false},{"id":"554435","x":518087.9,"y":11984429.9,"majorLevel":2.0,"majorInt":"Y","eligible":false},{"id":"554446","x":523992.2,"y":11985545.5,"majorLevel":2.0,"majorInt":"Y","eligible":false},{"id":"554447","x":524015.1,"y":11985480.3,"majorLevel":2.0,"majorInt":"Y","eligible":false},{"id":"554448","x":536441.2,"y":11987153.5,"majorLevel":2.0,"majorInt":"Y","eligible":false},{"id":"610172","x":554888.7,"y":11928762.1,"majorLevel":4.0,"majorInt":"N","eligible":true},{"id":"610205","x":557939.8,"y":11937091.3,"majorLevel":4.0,"majorInt":"N","eligible":true},{"id":"610625","x":506563.8,"y":11932749.4,"majorLevel":4.0,"majorInt":"N","eligible":true},{"id":"610627","x":506490.1,"y":11931627.6,"majorLevel":4.0,"majorInt":"N","eligible":true},{"id":"620562","x":545832.4,"y":11988337.1,"majorLevel":2.0,"majorInt":"Y","eligible":false},{"id":"656133","x":550582.5,"y":11939274.8,"majorLevel":4.0,"majorInt":"N","eligible":true},{"id":"656137","x":552927.2,"y":11938178.7,"majorLevel":4.0,"majorInt":"N","eligible":true},{"id":"656139","x":508052.0,"y":11925564.3,"majorLevel":4.0,"majorInt":"N","eligible":true},{"id":"670654","x":516253.5,"y":11994166.4,"majorLevel":4.0,"majorInt":"N","eligible":true},{"id":"670669","x":545449.2,"y":11996575.3,"majorLevel":4.0,"majorInt":"N","eligible":true},{"id":"670811","x":481798.3,"y":11978142.8,"majorLevel":2.0,"majorInt":"Y","eligible":false},{"id":"670812","x":481808.6,"y":11978073.8,"majorLevel":2.0,"majorInt":"Y","eligible":false},{"id":"670867","x":516220.2,"y":11988097.2,"majorLevel":5.0,"majorInt":"N","eligible":true},{"id":"670868","x":516370.0,"y":11987313.7,"majorLevel":5.0,"majorInt":"N","eligible":true},{"id":"671000","x":515107.5,"y":11963222.5,"majorLevel":4.0,"majorInt":"N","eligible":true},{"id":"671004","x":515187.8,"y":11963689.5,"majorLevel":4.0,"majorInt":"N","eligible":true},{"id":"674426","x":550496.8,"y":11986657.2,"majorLevel":2.0,"majorInt":"Y","eligible":false},{"id":"674427","x":550527.2,"y":11986708.6,"majorLevel":2.0,"majorInt":"Y","eligible":false},{"id":"674428","x":551621.7,"y":11985948.3,"majorLevel":2.0,"majorInt":"Y","eligible":false},{"id":"674429","x":551585.1,"y":11985893.1,"majorLevel":2.0,"majorInt":"Y","eligible":false},{"id":"674475","x":557938.7,"y":11982183.2,"majorLevel":2.0,"majorInt":"Y","eligible":false},{"id":"674476","x":557965.9,"y":11982238.2,"majorLevel":2.0,"majorInt":"Y","eligible":false},{"id":"674477","x":559343.5,"y":11981581.1,"majorLevel":2.0,"majorInt":"Y","eligible":false},{"id":"674478","x":559319.5,"y":11981518.9,"majorLevel":2.0,"majorInt":"Y","eligible":false},{"id":"674479","x":553094.2,"y":11984841.4,"majorLevel":2.0,"majorInt":"Y","eligible":false},{"id":"674480","x":553133.9,"y":11984893.0,"majorLevel":2.0,"majorInt":"Y","eligible":false},{"id":"692746","x":552791.9,"y":11938220.1,"majorLevel":4.0,"majorInt":"N","eligible":true},{"id":"692819","x":559527.8,"y":11940021.7,"majorLevel":4.0,"majorInt":"N","eligible":true},{"id":"711806","x":515967.9,"y":11977836.8,"majorLevel":4.0,"majorInt":"N","eligible":true},{"id":"711807","x":515794.7,"y":11978510.8,"majorLevel":4.0,"majorInt":"N","eligible":true},{"id":"725508","x":534963.6,"y":11956952.5,"majorLevel":4.0,"majorInt":"N","eligible":true},{"id":"726509","x":534329.4,"y":11955144.8,"majorLevel":4.0,"majorInt":"N","eligible":true},{"id":"748377","x":511894.0,"y":11947887.5,"majorLevel":4.0,"majorInt":"N","eligible":true},{"id":"748401","x":514511.8,"y":11959283.7,"majorLevel":4.0,"majorInt":"N","eligible":true},{"id":"748405","x":514797.7,"y":11961620.4,"majorLevel":4.0,"majorInt":"N","eligible":true},{"id":"748425","x":515280.7,"y":11966758.1,"majorLevel":4.0,"majorInt":"N","eligible":true},{"id":"748436","x":534750.6,"y":11962763.3,"majorLevel":4.0,"majorInt":"N","eligible":true},{"id":"748439","x":534500.7,"y":11963708.9,"majorLevel":4.0,"majorInt":"N","eligible":true},{"id":"748458","x":516993.3,"y":11982851.9,"majorLevel":4.0,"majorInt":"N","eligible":true},{"id":"748470","x":515278.9,"y":11980507.5,"majorLevel":4.0,"majorInt":"N","eligible":true},{"id":"748495","x":515735.0,"y":11978728.2,"majorLevel":4.0,"majorInt":"N","eligible":true},{"id":"748744","x":509999.4,"y":11944496.3,"majorLevel":4.0,"majorInt":"N","eligible":true},{"id":"834687","x":536126.0,"y":11987115.6,"majorLevel":2.0,"majorInt":"Y","eligible":false},{"id":"834693","x":534100.0,"y":11964881.3,"majorLevel":4.0,"majorInt":"N","eligible":true},{"id":"834709","x":541911.9,"y":11987763.1,"majorLevel":2.0,"majorInt":"Y","eligible":false},{"id":"834711","x":541881.4,"y":11987715.3,"majorLevel":2.0,"majorInt":"Y","eligible":false},{"id":"843750","x":533307.4,"y":11953316.4,"majorLevel":4.0,"majorInt":"N","eligible":true},{"id":"876356","x":544369.6,"y":11988123.7,"majorLevel":2.0,"majorInt":"Y","eligible":false},{"id":"876361","x":543842.9,"y":11988024.1,"majorLevel":2.0,"majorInt":"Y","eligible":false},{"id":"876362","x":543748.0,"y":11988091.6,"majorLevel":4.0,"majorInt":"N","eligible":true},{"id":"880202","x":515126.0,"y":11985693.4,"majorLevel":4.0,"majorInt":"N","eligible":true},{"id":"892124","x":533399.3,"y":11945295.0,"majorLevel":4.0,"majorInt":"N","eligible":true},{"id":"892125","x":533931.5,"y":11954403.4,"majorLevel":4.0,"majorInt":"N","eligible":true},{"id":"892126","x":534537.9,"y":11955803.1,"majorLevel":4.0,"majorInt":"N","eligible":true},{"id":"892127","x":533203.9,"y":11953140.0,"majorLevel":4.0,"majorInt":"N","eligible":true},{"id":"892128","x":532408.7,"y":11951016.9,"majorLevel":4.0,"majorInt":"N","eligible":true},{"id":"892129","x":536832.8,"y":11943600.4,"majorLevel":4.0,"majorInt":"N","eligible":true},{"id":"892130","x":532028.7,"y":11948372.9,"majorLevel":4.0,"majorInt":"N","eligible":true},{"id":"892131","x":554081.3,"y":11938070.6,"majorLevel":4.0,"majorInt":"N","eligible":true},{"id":"892132","x":558019.5,"y":11937005.3,"majorLevel":4.0,"majorInt":"N","eligible":true},{"id":"892133","x":550734.0,"y":11939200.9,"majorLevel":4.0,"majorInt":"N","eligible":true},{"id":"892134","x":551816.9,"y":11938662.2,"majorLevel":4.0,"majorInt":"N","eligible":true},{"id":"892135","x":538741.8,"y":11942867.4,"majorLevel":4.0,"majorInt":"N","eligible":true},{"id":"892136","x":548688.3,"y":11940021.9,"majorLevel":4.0,"majorInt":"N","eligible":true},{"id":"892137","x":556214.8,"y":11937997.3,"majorLevel":4.0,"majorInt":"N","eligible":true},{"id":"892138","x":556732.0,"y":11937966.0,"majorLevel":4.0,"majorInt":"N","eligible":true},{"id":"892139","x":559154.9,"y":11936151.2,"majorLevel":4.0,"majorInt":"N","eligible":true},{"id":"892178","x":557371.0,"y":11939810.6,"majorLevel":4.0,"majorInt":"N","eligible":true},{"id":"892894","x":506257.4,"y":11928211.1,"majorLevel":4.0,"majorInt":"N","eligible":true},{"id":"892898","x":510489.8,"y":11924284.7,"majorLevel":4.0,"majorInt":"N","eligible":true},{"id":"892899","x":512764.2,"y":11922245.9,"majorLevel":4.0,"majorInt":"N","eligible":true},{"id":"892942","x":508007.8,"y":11925589.1,"majorLevel":4.0,"majorInt":"N","eligible":true},{"id":"892946","x":512514.6,"y":11922587.7,"majorLevel":4.0,"majorInt":"N","eligible":true},{"id":"898853","x":514962.6,"y":11984544.7,"majorLevel":4.0,"majorInt":"N","eligible":true},{"id":"898865","x":515094.0,"y":11985543.7,"majorLevel":4.0,"majorInt":"N","eligible":true},{"id":"899275","x":515301.3,"y":11965637.8,"majorLevel":4.0,"majorInt":"N","eligible":true},{"id":"899276","x":515301.5,"y":11968635.8,"majorLevel":4.0,"majorInt":"N","eligible":true},{"id":"899277","x":516421.2,"y":11976042.9,"majorLevel":4.0,"majorInt":"N","eligible":true},{"id":"899278","x":508199.6,"y":11940822.8,"majorLevel":4.0,"majorInt":"N","eligible":true},{"id":"899279","x":507418.1,"y":11939722.9,"majorLevel":4.0,"majorInt":"N","eligible":true},{"id":"899280","x":512489.0,"y":11948882.8,"majorLevel":4.0,"majorInt":"N","eligible":true},{"id":"899281","x":513218.1,"y":11950909.8,"majorLevel":4.0,"majorInt":"N","eligible":true},{"id":"899282","x":514326.9,"y":11954678.3,"majorLevel":4.0,"majorInt":"N","eligible":true},{"id":"899283","x":514272.8,"y":11954331.8,"majorLevel":4.0,"majorInt":"N","eligible":true},{"id":"899284","x":516416.7,"y":11974132.7,"majorLevel":4.0,"majorInt":"N","eligible":true},{"id":"899285","x":510991.0,"y":11946370.9,"majorLevel":4.0,"majorInt":"N","eligible":true},{"id":"899286","x":515165.6,"y":11980949.6,"majorLevel":4.0,"majorInt":"N","eligible":true},{"id":"899287","x":514940.7,"y":11982539.7,"majorLevel":4.0,"majorInt":"N","eligible":true},{"id":"899288","x":515622.6,"y":11971107.7,"majorLevel":4.0,"majorInt":"N","eligible":true},{"id":"899289","x":515072.9,"y":11963032.8,"majorLevel":4.0,"majorInt":"N","eligible":true},{"id":"899448","x":535447.5,"y":11959536.4,"majorLevel":4.0,"majorInt":"N","eligible":true},{"id":"899449","x":535139.5,"y":11957297.4,"majorLevel":4.0,"majorInt":"N","eligible":true},{"id":"899450","x":522530.6,"y":11977929.1,"majorLevel":4.0,"majorInt":"N","eligible":true},{"id":"899451","x":516790.6,"y":11983816.5,"majorLevel":4.0,"majorInt":"N","eligible":true},{"id":"899452","x":533060.3,"y":11966108.8,"majorLevel":4.0,"majorInt":"N","eligible":true},{"id":"899458","x":535239.5,"y":11957499.1,"majorLevel":4.0,"majorInt":"N","eligible":true},{"id":"899459","x":534169.1,"y":11964675.0,"majorLevel":4.0,"majorInt":"N","eligible":true},{"id":"899545","x":517812.3,"y":11981867.8,"majorLevel":4.0,"majorInt":"N","eligible":true},{"id":"899546","x":523851.3,"y":11976094.4,"majorLevel":4.0,"majorInt":"N","eligible":true},{"id":"905334","x":514321.7,"y":11983738.0,"majorLevel":2.0,"majorInt":"Y","eligible":false},{"id":"908234","x":516431.5,"y":11974187.5,"majorLevel":4.0,"majorInt":"N","eligible":true},{"id":"914441","x":555271.8,"y":11938032.4,"majorLevel":4.0,"majorInt":"N","eligible":true},{"id":"929118","x":483529.1,"y":11978462.8,"majorLevel":2.0,"majorInt":"Y","eligible":false},{"id":"929130","x":482897.1,"y":11978275.3,"majorLevel":2.0,"majorInt":"Y","eligible":false},{"id":"929141","x":514172.0,"y":11983710.2,"majorLevel":2.0,"majorInt":"Y","eligible":false},{"id":"929147","x":515288.2,"y":11983916.8,"majorLevel":2.0,"majorInt":"Y","eligible":false},{"id":"929150","x":516357.5,"y":11984115.4,"majorLevel":2.0,"majorInt":"Y","eligible":false},{"id":"929154","x":515846.3,"y":11984020.1,"majorLevel":2.0,"majorInt":"Y","eligible":false},{"id":"929156","x":482272.3,"y":11978229.8,"majorLevel":2.0,"majorInt":"Y","eligible":false},{"id":"929157","x":482285.8,"y":11978160.8,"majorLevel":2.0,"majorInt":"Y","eligible":false},{"id":"929159","x":516828.9,"y":11983562.4,"majorLevel":4.0,"majorInt":"N","eligible":true},{"id":"929161","x":517392.6,"y":11984306.2,"majorLevel":2.0,"majorInt":"Y","eligible":false},{"id":"929170","x":498675.0,"y":11980878.3,"majorLevel":2.0,"majorInt":"Y","eligible":false},{"id":"929172","x":497937.9,"y":11980823.5,"majorLevel":2.0,"majorInt":"Y","eligible":false},{"id":"929174","x":498286.1,"y":11980752.4,"majorLevel":2.0,"majorInt":"Y","eligible":false},{"id":"929175","x":498201.7,"y":11980747.5,"majorLevel":2.0,"majorInt":"Y","eligible":false},{"id":"929176","x":497697.7,"y":11980783.5,"majorLevel":2.0,"majorInt":"Y","eligible":false},{"id":"929189","x":515094.9,"y":11983881.0,"majorLevel":2.0,"majorInt":"Y","eligible":false},{"id":"929199","x":514596.0,"y":11983789.5,"majorLevel":2.0,"majorInt":"Y","eligible":false},{"id":"929218","x":493661.4,"y":11980330.0,"majorLevel":2.0,"majorInt":"Y","eligible":false},{"id":"929220","x":494163.4,"y":11980421.2,"majorLevel":2.0,"majorInt":"Y","eligible":false},{"id":"929222","x":493968.0,"y":11980320.0,"majorLevel":2.0,"majorInt":"Y","eligible":false},{"id":"929223","x":492959.7,"y":11980203.1,"majorLevel":2.0,"majorInt":"Y","eligible":false},{"id":"929226","x":532120.4,"y":11986574.2,"majorLevel":2.0,"majorInt":"Y","eligible":false},{"id":"929227","x":493244.5,"y":11980185.5,"majorLevel":2.0,"majorInt":"Y","eligible":false},{"id":"929228","x":532562.4,"y":11986694.1,"majorLevel":2.0,"majorInt":"Y","eligible":false},{"id":"929229","x":514433.9,"y":11983757.9,"majorLevel":2.0,"majorInt":"Y","eligible":false},{"id":"929230","x":492745.5,"y":11980094.4,"majorLevel":2.0,"majorInt":"Y","eligible":false},{"id":"929231","x":514521.2,"y":11983773.8,"majorLevel":2.0,"majorInt":"Y","eligible":false},{"id":"929232","x":531536.8,"y":11986506.5,"majorLevel":2.0,"majorInt":"Y","eligible":false},{"id":"929233","x":531916.4,"y":11986621.8,"majorLevel":2.0,"majorInt":"Y","eligible":false},{"id":"929234","x":532819.3,"y":11986661.8,"majorLevel":2.0,"majorInt":"Y","eligible":false},{"id":"929240","x":488840.2,"y":11979443.3,"majorLevel":2.0,"majorInt":"Y","eligible":false},{"id":"929241","x":508135.5,"y":11982619.8,"majorLevel":2.0,"majorInt":"Y","eligible":false},{"id":"929242","x":489034.6,"y":11979406.2,"majorLevel":2.0,"majorInt":"Y","eligible":false},{"id":"929244","x":488915.0,"y":11979459.0,"majorLevel":2.0,"majorInt":"Y","eligible":false},{"id":"929246","x":488596.9,"y":11979399.7,"majorLevel":2.0,"majorInt":"Y","eligible":false},{"id":"929247","x":507746.8,"y":11982479.2,"majorLevel":2.0,"majorInt":"Y","eligible":false},{"id":"929256","x":482016.6,"y":11978182.4,"majorLevel":2.0,"majorInt":"Y","eligible":false},{"id":"929262","x":488020.0,"y":11979292.9,"majorLevel":2.0,"majorInt":"Y","eligible":false},{"id":"929265","x":502928.3,"y":11981663.2,"majorLevel":2.0,"majorInt":"Y","eligible":false},{"id":"929266","x":503464.6,"y":11981762.4,"majorLevel":2.0,"majorInt":"Y","eligible":false},{"id":"929271","x":503278.6,"y":11981657.6,"majorLevel":2.0,"majorInt":"Y","eligible":false},{"id":"929272","x":502524.0,"y":11981518.8,"majorLevel":2.0,"majorInt":"Y","eligible":false},{"id":"929274","x":501922.2,"y":11981407.8,"majorLevel":2.0,"majorInt":"Y","eligible":false},{"id":"929280","x":488304.9,"y":11979271.6,"majorLevel":2.0,"majorInt":"Y","eligible":false},{"id":"929284","x":488102.1,"y":11979235.9,"majorLevel":2.0,"majorInt":"Y","eligible":false},{"id":"929286","x":488239.4,"y":11979259.8,"majorLevel":2.0,"majorInt":"Y","eligible":false},{"id":"929289","x":487603.1,"y":11979144.9,"majorLevel":2.0,"majorInt":"Y","eligible":false},{"id":"929296","x":513299.0,"y":11983551.0,"majorLevel":2.0,"majorInt":"Y","eligible":false},{"id":"929298","x":533945.3,"y":11986829.2,"majorLevel":2.0,"majorInt":"Y","eligible":false},{"id":"929305","x":499321.6,"y":11980928.1,"majorLevel":2.0,"majorInt":"Y","eligible":false},{"id":"929307","x":500128.1,"y":11981147.7,"majorLevel":2.0,"majorInt":"Y","eligible":false},{"id":"929309","x":500496.1,"y":11981215.1,"majorLevel":2.0,"majorInt":"Y","eligible":false},{"id":"929316","x":489423.3,"y":11979553.8,"majorLevel":2.0,"majorInt":"Y","eligible":false},{"id":"929320","x":543055.2,"y":11987825.6,"majorLevel":2.0,"majorInt":"Y","eligible":false},{"id":"929321","x":543044.8,"y":11987883.6,"majorLevel":2.0,"majorInt":"Y","eligible":false},{"id":"929323","x":500101.2,"y":11981070.9,"majorLevel":2.0,"majorInt":"Y","eligible":false},{"id":"929326","x":480751.3,"y":11977880.1,"majorLevel":2.0,"majorInt":"Y","eligible":false},{"id":"929332","x":543245.5,"y":11987850.5,"majorLevel":2.0,"majorInt":"Y","eligible":false},{"id":"929336","x":543385.8,"y":11987871.0,"majorLevel":2.0,"majorInt":"Y","eligible":false},{"id":"929340","x":542490.4,"y":11987758.1,"majorLevel":2.0,"majorInt":"Y","eligible":false},{"id":"929342","x":541453.4,"y":11987697.4,"majorLevel":2.0,"majorInt":"Y","eligible":false},{"id":"929343","x":480123.4,"y":11977834.6,"majorLevel":2.0,"majorInt":"Y","eligible":false},{"id":"929344","x":544135.8,"y":11988079.8,"majorLevel":2.0,"majorInt":"Y","eligible":false},{"id":"929345","x":544890.1,"y":11988223.3,"majorLevel":2.0,"majorInt":"Y","eligible":false},{"id":"929354","x":480442.6,"y":11977824.7,"majorLevel":2.0,"majorInt":"Y","eligible":false},{"id":"929355","x":480675.5,"y":11977937.2,"majorLevel":2.0,"majorInt":"Y","eligible":false},{"id":"929532","x":539774.5,"y":11987506.1,"majorLevel":2.0,"majorInt":"Y","eligible":false},{"id":"929545","x":539861.9,"y":11987514.8,"majorLevel":2.0,"majorInt":"Y","eligible":false},{"id":"929557","x":540579.6,"y":11987599.4,"majorLevel":2.0,"majorInt":"Y","eligible":false},{"id":"929664","x":534441.5,"y":11986884.5,"majorLevel":2.0,"majorInt":"Y","eligible":false},{"id":"929667","x":534566.3,"y":11986897.5,"majorLevel":2.0,"majorInt":"Y","eligible":false},{"id":"929754","x":534248.0,"y":11986863.2,"majorLevel":2.0,"majorInt":"Y","eligible":false},{"id":"929799","x":540423.6,"y":11987582.3,"majorLevel":2.0,"majorInt":"Y","eligible":false},{"id":"929801","x":537777.1,"y":11987288.0,"majorLevel":2.0,"majorInt":"Y","eligible":false},{"id":"929802","x":537605.4,"y":11987274.3,"majorLevel":2.0,"majorInt":"Y","eligible":false},{"id":"929803","x":537486.8,"y":11987261.4,"majorLevel":2.0,"majorInt":"Y","eligible":false},{"id":"929805","x":537037.3,"y":11987221.4,"majorLevel":2.0,"majorInt":"Y","eligible":false},{"id":"929829","x":524185.4,"y":11985581.3,"majorLevel":2.0,"majorInt":"Y","eligible":false},{"id":"929830","x":523781.3,"y":11985436.6,"majorLevel":2.0,"majorInt":"Y","eligible":false},{"id":"929839","x":534844.0,"y":11986934.7,"majorLevel":2.0,"majorInt":"Y","eligible":false},{"id":"930373","x":533068.0,"y":11986749.5,"majorLevel":2.0,"majorInt":"Y","eligible":false},{"id":"930394","x":538401.4,"y":11987352.7,"majorLevel":2.0,"majorInt":"Y","eligible":false},{"id":"930721","x":513910.2,"y":11983658.8,"majorLevel":2.0,"majorInt":"Y","eligible":false},{"id":"935922","x":543842.1,"y":11988453.4,"majorLevel":4.0,"majorInt":"N","eligible":true},{"id":"950490","x":535525.4,"y":11958205.9,"majorLevel":4.0,"majorInt":"N","eligible":true},{"id":"1013568","x":545913.4,"y":11988353.0,"majorLevel":2.0,"majorInt":"Y","eligible":false},{"id":"1013573","x":549075.2,"y":11987725.0,"majorLevel":2.0,"majorInt":"Y","eligible":false},{"id":"1013574","x":544386.3,"y":11990903.7,"majorLevel":4.0,"majorInt":"N","eligible":true},{"id":"1027952","x":544593.2,"y":11992384.3,"majorLevel":4.0,"majorInt":"N","eligible":true},{"id":"1037803","x":488495.9,"y":11979460.0,"majorLevel":5.0,"majorInt":"N","eligible":true},{"id":"1037804","x":488409.8,"y":11979364.2,"majorLevel":2.0,"majorInt":"Y","eligible":false},{"id":"1042620","x":516656.8,"y":11984171.0,"majorLevel":2.0,"majorInt":"Y","eligible":false},{"id":"1042621","x":516831.4,"y":11984202.8,"majorLevel":2.0,"majorInt":"Y","eligible":false},{"id":"1062460","x":531624.8,"y":11966857.0,"majorLevel":4.0,"majorInt":"N","eligible":true},{"id":"1062494","x":526523.1,"y":11969758.8,"majorLevel":4.0,"majorInt":"N","eligible":true},{"id":"1062509","x":528580.9,"y":11967837.8,"majorLevel":4.0,"majorInt":"N","eligible":true},{"id":"1062763","x":543213.3,"y":11987904.6,"majorLevel":2.0,"majorInt":"Y","eligible":false},{"id":"1062764","x":537886.4,"y":11987297.0,"majorLevel":2.0,"majorInt":"Y","eligible":false},{"id":"1062791","x":544495.3,"y":11988082.1,"majorLevel":2.0,"majorInt":"Y","eligible":false},{"id":"1062793","x":525421.3,"y":11972360.9,"majorLevel":4.0,"majorInt":"N","eligible":true},{"id":"1062794","x":524816.7,"y":11973799.4,"majorLevel":4.0,"majorInt":"N","eligible":true},{"id":"1063162","x":514978.4,"y":11984734.2,"majorLevel":4.0,"majorInt":"N","eligible":true},{"id":"1063163","x":512999.4,"y":11983513.6,"majorLevel":2.0,"majorInt":"Y","eligible":false},{"id":"1063165","x":511814.6,"y":11983298.8,"majorLevel":2.0,"majorInt":"Y","eligible":false},{"id":"1063169","x":487774.7,"y":11979176.5,"majorLevel":2.0,"majorInt":"Y","eligible":false},{"id":"1063181","x":511238.9,"y":11983122.5,"majorLevel":2.0,"majorInt":"Y","eligible":false},{"id":"1063182","x":509895.1,"y":11982872.5,"majorLevel":2.0,"majorInt":"Y","eligible":false},{"id":"1063183","x":510936.4,"y":11983066.9,"majorLevel":2.0,"majorInt":"Y","eligible":false},{"id":"1063185","x":508769.5,"y":11982665.9,"majorLevel":2.0,"majorInt":"Y","eligible":false},{"id":"1063187","x":489223.7,"y":11979518.1,"majorLevel":2.0,"majorInt":"Y","eligible":false},{"id":"1063188","x":504765.9,"y":11981931.4,"majorLevel":2.0,"majorInt":"Y","eligible":false},{"id":"1063189","x":480769.0,"y":11977953.2,"majorLevel":2.0,"majorInt":"Y","eligible":false},{"id":"1063190","x":505670.2,"y":11982098.0,"majorLevel":2.0,"majorInt":"Y","eligible":false},{"id":"1063191","x":506353.0,"y":11982221.3,"majorLevel":2.0,"majorInt":"Y","eligible":false},{"id":"1063193","x":507405.8,"y":11982488.5,"majorLevel":2.0,"majorInt":"Y","eligible":false},{"id":"1063194","x":509922.0,"y":11982953.0,"majorLevel":2.0,"majorInt":"Y","eligible":false},{"id":"1063195","x":510938.4,"y":11983139.7,"majorLevel":2.0,"majorInt":"Y","eligible":false},{"id":"1063197","x":555194.8,"y":11932358.6,"majorLevel":4.0,"majorInt":"N","eligible":true},{"id":"1063201","x":555314.0,"y":11934587.4,"majorLevel":4.0,"majorInt":"N","eligible":true},{"id":"1063214","x":515149.3,"y":11985802.9,"majorLevel":4.0,"majorInt":"N","eligible":true},{"id":"1063233","x":481355.4,"y":11978059.9,"majorLevel":2.0,"majorInt":"Y","eligible":false},{"id":"1063243","x":481368.9,"y":11977994.6,"majorLevel":2.0,"majorInt":"Y","eligible":false},{"id":"1063682","x":514929.3,"y":11984071.2,"majorLevel":4.0,"majorInt":"N","eligible":true},{"id":"1063725","x":506361.3,"y":11982294.2,"majorLevel":2.0,"majorInt":"Y","eligible":false},{"id":"1063726","x":505675.3,"y":11982167.3,"majorLevel":2.0,"majorInt":"Y","eligible":false},{"id":"1063758","x":514484.1,"y":11957846.1,"majorLevel":4.0,"majorInt":"N","eligible":true},{"id":"1063761","x":509281.9,"y":11942917.1,"majorLevel":4.0,"majorInt":"N","eligible":true},{"id":"1063762","x":514459.5,"y":11956412.2,"majorLevel":4.0,"majorInt":"N","eligible":true},{"id":"1063763","x":512577.5,"y":11949029.7,"majorLevel":4.0,"majorInt":"N","eligible":true},{"id":"1063764","x":507072.5,"y":11939186.4,"majorLevel":4.0,"majorInt":"N","eligible":true},{"id":"1063765","x":506918.6,"y":11938401.8,"majorLevel":4.0,"majorInt":"N","eligible":true},{"id":"1063766","x":514950.2,"y":11982932.8,"majorLevel":4.0,"majorInt":"N","eligible":true},{"id":"1064285","x":556092.6,"y":11938002.5,"majorLevel":4.0,"majorInt":"N","eligible":true},{"id":"1064306","x":559181.0,"y":11939975.8,"majorLevel":4.0,"majorInt":"N","eligible":true},{"id":"1064892","x":558734.1,"y":11939931.8,"majorLevel":4.0,"majorInt":"N","eligible":true},{"id":"1064936","x":558796.6,"y":11939936.5,"majorLevel":4.0,"majorInt":"N","eligible":true},{"id":"1071638","x":544174.2,"y":11989735.9,"majorLevel":4.0,"majorInt":"N","eligible":true},{"id":"1352073","x":555419.9,"y":11938158.6,"majorLevel":4.0,"majorInt":"N","eligible":true},{"id":"1352075","x":555431.0,"y":11938246.1,"majorLevel":4.0,"majorInt":"N","eligible":true},{"id":"1367390","x":548781.1,"y":11987931.2,"majorLevel":2.0,"majorInt":"Y","eligible":false},{"id":"1367530","x":544506.6,"y":11991757.1,"majorLevel":4.0,"majorInt":"N","eligible":true},{"id":"1367557","x":544767.6,"y":11993369.5,"majorLevel":4.0,"majorInt":"N","eligible":true},{"id":"1367741","x":548738.1,"y":11987879.5,"majorLevel":2.0,"majorInt":"Y","eligible":false},{"id":"1458018","x":552162.7,"y":11985568.0,"majorLevel":2.0,"majorInt":"Y","eligible":false},{"id":"1458448","x":555021.6,"y":11983647.6,"majorLevel":2.0,"majorInt":"Y","eligible":false},{"id":"1458449","x":552562.7,"y":11985210.9,"majorLevel":2.0,"majorInt":"Y","eligible":false},{"id":"1527964","x":537138.9,"y":11943448.9,"majorLevel":4.0,"majorInt":"N","eligible":true},{"id":"1527968","x":556300.0,"y":11939636.1,"majorLevel":4.0,"majorInt":"N","eligible":true},{"id":"1528014","x":533703.1,"y":11954006.8,"majorLevel":4.0,"majorInt":"N","eligible":true},{"id":"1528106","x":541563.3,"y":11942058.5,"majorLevel":4.0,"majorInt":"N","eligible":true},{"id":"1528218","x":545369.5,"y":11940971.2,"majorLevel":4.0,"majorInt":"N","eligible":true},{"id":"1528219","x":548858.2,"y":11939973.8,"majorLevel":4.0,"majorInt":"N","eligible":true},{"id":"1528260","x":532951.2,"y":11952699.3,"majorLevel":4.0,"majorInt":"N","eligible":true},{"id":"1528276","x":510726.7,"y":11924161.0,"majorLevel":4.0,"majorInt":"N","eligible":true},{"id":"1528315","x":542629.6,"y":11941755.7,"majorLevel":4.0,"majorInt":"N","eligible":true},{"id":"1528454","x":506240.9,"y":11927450.4,"majorLevel":4.0,"majorInt":"N","eligible":true},{"id":"1573797","x":524761.4,"y":11973929.5,"majorLevel":4.0,"majorInt":"N","eligible":true},{"id":"1624921","x":516201.5,"y":11976898.1,"majorLevel":4.0,"majorInt":"N","eligible":true},{"id":"1642961","x":544327.6,"y":11990480.7,"majorLevel":4.0,"majorInt":"N","eligible":true},{"id":"1666866","x":542748.4,"y":11987846.0,"majorLevel":2.0,"majorInt":"Y","eligible":false},{"id":"1667343","x":502257.9,"y":11981540.2,"majorLevel":2.0,"majorInt":"Y","eligible":false},{"id":"1667344","x":503493.7,"y":11981697.3,"majorLevel":2.0,"majorInt":"Y","eligible":false},{"id":"1669512","x":517826.0,"y":11984385.8,"majorLevel":2.0,"majorInt":"Y","eligible":false},{"id":"1687974","x":543594.8,"y":11987903.6,"majorLevel":2.0,"majorInt":"Y","eligible":false},{"id":"1695805","x":522396.1,"y":11977934.2,"majorLevel":5.0,"majorInt":"N","eligible":true},{"id":"1705249","x":558086.5,"y":11936930.0,"majorLevel":4.0,"majorInt":"N","eligible":true},{"id":"1718155","x":514182.9,"y":11921059.9,"majorLevel":4.0,"majorInt":"N","eligible":true},{"id":"1730268","x":516091.9,"y":11972901.4,"majorLevel":4.0,"majorInt":"N","eligible":true}]}